harlequelrah/__init__.py
harlequelrah/utilitaire.py
harlequelrah/django/__init__.py
harlequelrah/django/functions.py
harlequelrah/django/validators.py
harlequelrah/django/views.py
harlequelrah/files/__init__.py
harlequelrah/files/myfiles.py
harlequelrah/integer/__init__.py
harlequelrah/integer/myint.py
harlequelrah/string/__init__.py
harlequelrah/string/mychar.py
harlequelrah/string/mycryptography.py
harlequelrah/string/mysequence.py
harlequelrah/turtle/__init__.py
harlequelrah/turtle/myturtle.py
harlequelrah-0.1.dist-info/METADATA
harlequelrah-0.1.dist-info/WHEEL
harlequelrah-0.1.dist-info/top_level.txt
harlequelrah-0.1.dist-info/RECORD
